LICENSE
MANIFEST.in
README.rst
setup.cfg
setup.py
SUITPy/__init__.py
SUITPy/atlas.py
SUITPy/flatmap.py
SUITPy/reslice.py
SUITPy/utils.py
SUITPy.egg-info/PKG-INFO
SUITPy.egg-info/SOURCES.txt
SUITPy.egg-info/dependency_links.txt
SUITPy.egg-info/not-zip-safe
SUITPy.egg-info/requires.txt
SUITPy.egg-info/top_level.txt
SUITPy/_utils/__init__.py
SUITPy/_utils/docs.py
SUITPy/surfaces/FLAT.surf.gii
SUITPy/surfaces/PIAL_FSL.surf.gii
SUITPy/surfaces/PIAL_MNISymC.surf.gii
SUITPy/surfaces/PIAL_SPM.surf.gii
SUITPy/surfaces/PIAL_SUIT.surf.gii
SUITPy/surfaces/SUIT.C.scene
SUITPy/surfaces/SUIT.shape.gii
SUITPy/surfaces/WHITE_FSL.surf.gii
SUITPy/surfaces/WHITE_MNISymC.surf.gii
SUITPy/surfaces/WHITE_SPM.surf.gii
SUITPy/surfaces/WHITE_SUIT.surf.gii
SUITPy/surfaces/borders.txt