Metadata-Version: 1.2
Name: SUITPy
Version: 1.3.2
Summary: Mapping and plotting cerebellar fMRI data in Python
Home-page: https://github.com/DiedrichsenLab/SUITPy
Maintainer: Jorn Diedrichsen
Maintainer-email: joern.diedrichsen@googlemail.com
License: MIT
Download-URL: https://github.com/DiedrichsenLab/SUITPy/archive/refs/tags/v.1.3.2.tar.gz
Platform: UNKNOWN
Classifier: Intended Audience :: Science/Research
Classifier: Intended Audience :: Developers
Classifier: License :: OSI Approved
Classifier: Programming Language :: Python
Classifier: Topic :: Software Development
Classifier: Topic :: Scientific/Engineering
Classifier: Operating System :: Microsoft :: Windows
Classifier: Operating System :: POSIX
Classifier: Operating System :: Unix
Classifier: Operating System :: MacOS
Classifier: Programming Language :: Python :: 3.6
Classifier: Programming Language :: Python :: 3.7
Classifier: Programming Language :: Python :: 3.8
Classifier: Programming Language :: Python :: 3.9
Requires-Python: >=3.6
